rendercanvas/__init__.py
rendercanvas/_coreutils.py
rendercanvas/_enums.py
rendercanvas/_events.py
rendercanvas/_loop.py
rendercanvas/_scheduler.py
rendercanvas/_size.py
rendercanvas/_version.py
rendercanvas/asyncio.py
rendercanvas/auto.py
rendercanvas/base.py
rendercanvas/glfw.py
rendercanvas/jupyter.py
rendercanvas/offscreen.py
rendercanvas/pyodide.py
rendercanvas/pyqt5.py
rendercanvas/pyqt6.py
rendercanvas/pyside2.py
rendercanvas/pyside6.py
rendercanvas/qt.py
rendercanvas/raw.py
rendercanvas/stub.py
rendercanvas/trio.py
rendercanvas/wx.py
rendercanvas/__pyinstaller/__init__.py
rendercanvas/__pyinstaller/conftest.py
rendercanvas/__pyinstaller/hook-rendercanvas.py
rendercanvas/__pyinstaller/test_rendercanvas.py
rendercanvas/contexts/__init__.py
rendercanvas/contexts/_fullscreen.py
rendercanvas/contexts/basecontext.py
rendercanvas/contexts/bitmapcontext.py
rendercanvas/contexts/wgpucontext.py
rendercanvas/utils/__init__.py
rendercanvas/utils/asyncadapter.py
rendercanvas/utils/asyncs.py
rendercanvas/utils/cube.py
rendercanvas-2.5.2.dist-info/entry_points.txt
rendercanvas-2.5.2.dist-info/licenses/LICENSE
rendercanvas-2.5.2.dist-info/WHEEL
rendercanvas-2.5.2.dist-info/METADATA
rendercanvas-2.5.2.dist-info/RECORD
