Metadata-Version: 2.4
Name: rendercanvas
Version: 2.5.2
Summary: One canvas API, multiple backends
Keywords: canvas,rendering,graphics,wgpu,qt,wx,glfw,jupyter
Author: Almar Klein, Korijn van Golen
Requires-Python: >= 3.10
License-File: LICENSE
Requires-Dist: rendercanvas[lint, tests, examples, docs] ; extra == "dev"
Requires-Dist: flit ; extra == "docs"
Requires-Dist: sphinx>7.2 ; extra == "docs"
Requires-Dist: sphinx_rtd_theme ; extra == "docs"
Requires-Dist: sphinx-gallery ; extra == "docs"
Requires-Dist: numpy ; extra == "docs"
Requires-Dist: wgpu ; extra == "docs"
Requires-Dist: flit ; extra == "examples"
Requires-Dist: numpy ; extra == "examples"
Requires-Dist: wgpu ; extra == "examples"
Requires-Dist: glfw ; extra == "examples"
Requires-Dist: pyside6 ; extra == "examples"
Requires-Dist: imageio ; extra == "examples"
Requires-Dist: pytest ; extra == "examples"
Requires-Dist: glfw>=1.9 ; extra == "glfw"
Requires-Dist: jupyter_rfb>=0.4.2 ; extra == "jupyter"
Requires-Dist: ruff ; extra == "lint"
Requires-Dist: pre-commit ; extra == "lint"
Requires-Dist: pytest ; extra == "tests"
Requires-Dist: numpy ; extra == "tests"
Requires-Dist: wgpu ; extra == "tests"
Requires-Dist: glfw ; extra == "tests"
Requires-Dist: trio ; extra == "tests"
Project-URL: Documentation, https://rendercanvas.readthedocs.io
Project-URL: Homepage, https://github.com/pygfx/rendercanvas
Project-URL: Repository, https://github.com/pygfx/rendercanvas
Provides-Extra: dev
Provides-Extra: docs
Provides-Extra: examples
Provides-Extra: glfw
Provides-Extra: jupyter
Provides-Extra: lint
Provides-Extra: tests
